{
	"name": "KLD_BLOB_OUTPUT",
	"properties": {
		"linkedServiceName": {
			"referenceName": "AZURE_BLOB_LINK",
			"type": "LinkedServiceReference"
		},
		"parameters": {
			"sheetName": {
				"type": "string"
			},
			"fileName": {
				"type": "string"
			}
		},
		"annotations": [],
		"type": "Excel",
		"typeProperties": {
			"sheetName": {
				"value": "@dataset().sheetName",
				"type": "Expression"
			},
			"location": {
				"type": "AzureBlobStorageLocation",
				"fileName": {
					"value": "@dataset().fileName",
					"type": "Expression"
				},
				"container": "utslippdata"
			},
			"firstRowAsHeader": true
		},
		"schema": []
	}
}